youtube_unlimited_search/__init__.py
youtube_unlimited_search-0.3.2.dist-info/LICENSE
youtube_unlimited_search-0.3.2.dist-info/METADATA
youtube_unlimited_search-0.3.2.dist-info/WHEEL
youtube_unlimited_search-0.3.2.dist-info/top_level.txt
youtube_unlimited_search-0.3.2.dist-info/RECORD
