Metadata-Version: 2.1
Name: youtube-unlimited-search
Version: 0.3.2
Summary: Allow you to search in youtube without care about requests limitation
Home-page: https://github.com/HatemEng/Youtube_Unlimited_Search
Author: Hatem Karim
Author-email: hatemkarimen@gmail.com
License: UNKNOWN
Platform: UNKNOWN
Classifier: Programming Language :: Python :: 3
Classifier: License :: OSI Approved :: MIT License
Classifier: Operating System :: OS Independent
Requires-Python: >=3.6
Requires-Dist: requests
Requires-Dist: beautifulsoup4
